{
  "book": "yoel",
  "book_he": "יוֹאֵל",
  "book_es": "Joel",
  "chapter": 1,
  "title_he": "יואל",
  "verses": [
    {
      "num": 1,
      "he": "דְּבַר־יְהֹוָה֙ אֲשֶׁ֣ר הָיָ֔ה אֶל־יוֹאֵ֖ל בֶּן־פְּתוּאֵֽל׃",
      "es": "Palabra del Eterno que fue a Yoel hijo de Petuel."
    },
    {
      "num": 2,
      "he": "שִׁמְעוּ־זֹאת֙ הַזְּקֵנִ֔ים וְהַֽאֲזִ֔ינוּ כֹּ֖ל יוֹשְׁבֵ֣י הָאָ֑רֶץ הֶהָ֤יְתָה זֹּאת֙ בִּֽימֵיכֶ֔ם וְאִ֖ם בִּימֵ֥י אֲבֹתֵיכֶֽם׃",
      "es": "Escuchad esto, ancianos, y prestad oído, todos los moradores de la tierra: ¿Ha acontecido esto en vuestros días, o en los días de vuestros padres?"
    },
    {
      "num": 3,
      "he": "עָלֶ֖יהָ לִבְנֵיכֶ֣ם סַפֵּ֑רוּ וּבְנֵיכֶם֙ לִבְנֵיהֶ֔ם וּבְנֵיהֶ֖ם לְד֥וֹר אַחֵֽר׃",
      "es": "Sobre ello a vuestros hijos contad, y vuestros hijos a sus hijos, y sus hijos a la generación siguiente."
    },
    {
      "num": 4,
      "he": "יֶ֤תֶר הַגָּזָם֙ אָכַ֣ל הָאַרְבֶּ֔ה וְיֶ֥תֶר הָאַרְבֶּ֖ה אָכַ֣ל הַיָּ֑לֶק וְיֶ֣תֶר הַיֶּ֔לֶק אָכַ֖ל הֶחָסִֽיל׃",
      "es": "Lo que dejó el gazam, comió la langosta; y lo que dejó la langosta, comió el yélek; y lo que dejó el yélek, comió el jasil.",
      "nota": "jasil — Heb. חָסִיל (jasil), tipo de langosta o insecto devorador cuya identificación exacta es debatida. Se mantiene en hebreo por falta de correspondencia unívoca."
    },
    {
      "num": 5,
      "he": "הָקִ֤יצוּ שִׁכּוֹרִים֙ וּבְכ֔וּ וְהֵילִ֖לוּ כׇּל־שֹׁ֣תֵי יָ֑יִן עַל־עָסִ֕יס כִּ֥י נִכְרַ֖ת מִפִּיכֶֽם׃",
      "es": "Despertad, ebrios, y llorad; y gemid, todos los bebedores de vino, por el mosto, pues ha sido cortado de vuestra boca."
    },
    {
      "num": 6,
      "he": "כִּי־גוֹי֙ עָלָ֣ה עַל־אַרְצִ֔י עָצ֖וּם וְאֵ֣ין מִסְפָּ֑ר שִׁנָּיו֙ שִׁנֵּ֣י אַרְיֵ֔ה וּֽמְתַלְּע֥וֹת לָבִ֖יא לֽוֹ׃",
      "es": "Porque un pueblo subió sobre mi tierra, poderoso y sin número; sus dientes son dientes de león, y colmillos de leona tiene."
    },
    {
      "num": 7,
      "he": "שָׂ֤ם גַּפְנִי֙ לְשַׁמָּ֔ה וּתְאֵנָתִ֖י לִקְצָפָ֑ה חָשֹׂ֤ף חֲשָׂפָהּ֙ וְהִשְׁלִ֔יךְ הִלְבִּ֖ינוּ שָׂרִיגֶֽיהָ׃",
      "es": "Puso mi vid en desolación, y mi higuera en astillas; la descortezó por completo y la arrojó; blanquearon sus sarmientos."
    },
    {
      "num": 8,
      "he": "אֱלִ֕י כִּבְתוּלָ֥ה חֲגֻרַת־שַׂ֖ק עַל־בַּ֥עַל נְעוּרֶֽיהָ׃",
      "es": "Gime como doncella ceñida de saco por el esposo de su juventud."
    },
    {
      "num": 9,
      "he": "הׇכְרַ֥ת מִנְחָ֛ה וָנֶ֖סֶךְ מִבֵּ֣ית יְהֹוָ֑ה אָֽבְלוּ֙ הַכֹּ֣הֲנִ֔ים מְשָׁרְתֵ֖י יְהֹוָֽה׃",
      "es": "Fue cortada la ofrenda y la libación de la Casa del Eterno; están de duelo los cohanim, servidores del Eterno.",
      "nota": "cohanim — Plural de cohen; sacerdotes que sirven en el Templo."
    },
    {
      "num": 10,
      "he": "שֻׁדַּ֣ד שָׂדֶ֔ה אָבְלָ֖ה אֲדָמָ֑ה כִּ֚י שֻׁדַּ֣ד דָּגָ֔ן הוֹבִ֥ישׁ תִּיר֖וֹשׁ אֻמְלַ֥ל יִצְהָֽר׃",
      "es": "Fue devastado el campo, está de duelo la tierra, porque fue devastado el grano, se secó el mosto, languideció el aceite."
    },
    {
      "num": 11,
      "he": "הֹבִ֣ישׁוּ אִכָּרִ֗ים הֵילִ֙ילוּ֙ כֹּֽרְמִ֔ים עַל־חִטָּ֖ה וְעַל־שְׂעֹרָ֑ה כִּ֥י אָבַ֖ד קְצִ֥יר שָׂדֶֽה׃",
      "es": "Avergonzaos, labradores; gemid, viñadores, por el trigo y por la cebada, porque pereció la cosecha del campo."
    },
    {
      "num": 12,
      "he": "הַגֶּ֣פֶן הוֹבִ֔ישָׁה וְהַתְּאֵנָ֖ה אֻמְלָ֑לָה רִמּ֞וֹן גַּם־תָּמָ֣ר וְתַפּ֗וּחַ כׇּל־עֲצֵ֤י הַשָּׂדֶה֙ יָבֵ֔שׁוּ כִּי־הֹבִ֥ישׁ שָׂשׂ֖וֹן מִן־בְּנֵ֥י אָדָֽם׃&nbsp;<span class=\"mam-spi-samekh\">{ס}</span>&nbsp;&nbsp;&nbsp;&nbsp;&nbsp;&nbsp;&nbsp;&nbsp;",
      "es": "La vid se secó y la higuera languideció; el granado, también la palmera y el manzano, todos los árboles del campo se secaron, pues se secó el gozo de los hijos del hombre."
    },
    {
      "num": 13,
      "he": "חִגְר֨וּ וְסִפְד֜וּ הַכֹּהֲנִ֗ים הֵילִ֙ילוּ֙ מְשָׁרְתֵ֣י מִזְבֵּ֔חַ בֹּ֚אוּ לִ֣ינוּ בַשַּׂקִּ֔ים מְשָׁרְתֵ֖י אֱלֹהָ֑י כִּ֥י נִמְנַ֛ע מִבֵּ֥ית אֱלֹהֵיכֶ֖ם מִנְחָ֥ה וָנָֽסֶךְ׃",
      "es": "Ceñíos y lamentad, cohanim; gemid, servidores del altar; venid, pasad la noche en sacos, servidores de mi Elohim, pues ha sido retenida de la Casa de vuestro Elohim la ofrenda y la libación.",
      "nota": "cohanim — Véase nota al versículo 9."
    },
    {
      "num": 14,
      "he": "קַדְּשׁוּ־צוֹם֙ קִרְא֣וּ עֲצָרָ֔ה אִסְפ֣וּ זְקֵנִ֗ים כֹּ֚ל יֹשְׁבֵ֣י הָאָ֔רֶץ בֵּ֖ית יְהֹוָ֣ה אֱלֹהֵיכֶ֑ם וְזַעֲק֖וּ אֶל־יְהֹוָֽה׃",
      "es": "Santificad ayuno, convocad asamblea solemne, reunid a los ancianos, a todos los moradores de la tierra, en la Casa del Eterno vuestro Elohim, y clamad al Eterno."
    },
    {
      "num": 15,
      "he": "אֲהָ֖הּ לַיּ֑וֹם כִּ֤י קָרוֹב֙ י֣וֹם יְהֹוָ֔ה וּכְשֹׁ֖ד מִשַּׁדַּ֥י יָבֽוֹא׃",
      "es": "¡Ay de aquel día! Pues cercano está el día del Eterno, y como destrucción de Shaday vendrá.",
      "nota": "Shaday — Nombre divino; aquí el texto emplea un juego de palabras entre שֹׁד (shod, «destrucción») y שַׁדַּי (Shaday)."
    },
    {
      "num": 16,
      "he": "הֲל֛וֹא נֶ֥גֶד עֵינֵ֖ינוּ אֹ֣כֶל נִכְרָ֑ת מִבֵּ֥ית אֱלֹהֵ֖ינוּ שִׂמְחָ֥ה וָגִֽיל׃",
      "es": "¿Acaso no ante nuestros ojos el alimento fue cortado, y de la Casa de nuestro Elohim la alegría y el júbilo?"
    },
    {
      "num": 17,
      "he": "עָבְשׁ֣וּ פְרֻד֗וֹת תַּ֚חַת מֶגְרְפֹ֣תֵיהֶ֔ם נָשַׁ֙מּוּ֙ אֹֽצָר֔וֹת נֶהֶרְס֖וּ מַמְּגֻר֑וֹת כִּ֥י הֹבִ֖ישׁ דָּגָֽן׃",
      "es": "Se pudrieron las semillas bajo sus terrones, quedaron desolados los graneros, fueron derribados los almacenes, pues se secó el grano."
    },
    {
      "num": 18,
      "he": "מַה־נֶּאֶנְחָ֣ה בְהֵמָ֗ה נָבֹ֙כוּ֙ עֶדְרֵ֣י בָקָ֔ר כִּ֛י אֵ֥ין מִרְעֶ֖ה לָהֶ֑ם גַּם־עֶדְרֵ֥י הַצֹּ֖אן נֶאְשָֽׁמוּ׃",
      "es": "¡Cómo gime la bestia! Andan confusos los rebaños de ganado vacuno, porque no hay pasto para ellos; también los rebaños de ovejas padecen."
    },
    {
      "num": 19,
      "he": "אֵלֶ֥יךָ יְהֹוָ֖ה אֶקְרָ֑א כִּ֣י אֵ֗שׁ אָֽכְלָה֙ נְא֣וֹת מִדְבָּ֔ר וְלֶ֣הָבָ֔ה לִהֲטָ֖ה כׇּל־עֲצֵ֥י הַשָּׂדֶֽה׃",
      "es": "A Ti, oh Eterno, clamo, porque el fuego devoró los pastizales del desierto, y la llama abrasó todos los árboles del campo."
    },
    {
      "num": 20,
      "he": "גַּם־בַּהֲמ֥וֹת שָׂדֶ֖ה תַּעֲר֣וֹג אֵלֶ֑יךָ כִּ֤י יָֽבְשׁוּ֙ אֲפִ֣יקֵי מָ֔יִם וְאֵ֕שׁ אָכְלָ֖ה נְא֥וֹת הַמִּדְבָּֽר׃&nbsp;<span class=\"mam-spi-samekh\">{ס}</span>&nbsp;&nbsp;&nbsp;&nbsp;&nbsp;&nbsp;&nbsp;&nbsp;",
      "es": "También las bestias del campo claman a Ti, porque se secaron los cauces de agua, y el fuego devoró los pastizales del desierto."
    }
  ]
}