{
  "book": "hoshea",
  "book_he": "הוֹשֵׁעַ",
  "book_es": "Oseas",
  "chapter": 9,
  "title_he": "הושע",
  "verses": [
    {
      "num": 1,
      "he": "אַל־תִּשְׂמַ֨ח יִשְׂרָאֵ֤ל&thinsp;<small>׀</small>&thinsp;אֶל־גִּיל֙ כָּעַמִּ֔ים כִּ֥י זָנִ֖יתָ מֵעַ֣ל אֱלֹהֶ֑יךָ אָהַ֣בְתָּ אֶתְנָ֔ן עַ֖ל כׇּל־גׇּרְנ֥וֹת דָּגָֽן׃",
      "es": "No te regociges, Yisrael, hasta el júbilo como los pueblos, pues has fornicado apartándote de tu Elohim; has amado la paga de ramera sobre todas las eras de trigo.",
      "nota": "ELOHIM — Nombre divino que designa a Dios en su atributo de poder y juicio."
    },
    {
      "num": 2,
      "he": "גֹּ֥רֶן וָיֶ֖קֶב לֹ֣א יִרְעֵ֑ם וְתִיר֖וֹשׁ יְכַ֥חֶשׁ בָּֽהּ׃",
      "es": "La era y el lagar no los alimentarán, y el mosto les fallará."
    },
    {
      "num": 3,
      "he": "לֹ֥א יֵשְׁב֖וּ בְּאֶ֣רֶץ יְהֹוָ֑ה וְשָׁ֤ב אֶפְרַ֙יִם֙ מִצְרַ֔יִם וּבְאַשּׁ֖וּר טָמֵ֥א יֹאכֵֽלוּ׃",
      "es": "No habitarán en la tierra del Eterno; y volverá Efráyim a Mitsráyim, y en Ashur comerán lo impuro."
    },
    {
      "num": 4,
      "he": "לֹא־יִסְּכ֨וּ לַיהֹוָ֥ה&thinsp;<small>׀</small>&thinsp;יַ֘יִן֮ וְלֹ֣א יֶעֶרְבוּ־לוֹ֒ זִבְחֵיהֶ֗ם כְּלֶ֤חֶם אוֹנִים֙ לָהֶ֔ם כׇּל־אֹכְלָ֖יו יִטַּמָּ֑אוּ כִּֽי־לַחְמָ֣ם לְנַפְשָׁ֔ם לֹ֥א יָב֖וֹא בֵּ֥ית יְהֹוָֽה׃",
      "es": "No derramarán vino al Eterno, y no le serán gratos sus sacrificios; como pan de duelo será para ellos, todo el que lo coma quedará impuro, pues su pan será para ellos mismos, no entrará en la Casa del Eterno.",
      "nota": "PAN DE DUELO — Heb. לֶחֶם אוֹנִים (léjem onim), pan asociado al duelo, que transmite impureza ritual a quien lo consume."
    },
    {
      "num": 5,
      "he": "מַֽה־תַּעֲשׂ֖וּ לְי֣וֹם מוֹעֵ֑ד וּלְי֖וֹם חַג־יְהֹוָֽה׃",
      "es": "¿Qué haréis para el día de la festividad, y para el día de la fiesta del Eterno?"
    },
    {
      "num": 6,
      "he": "כִּֽי־הִנֵּ֤ה הָֽלְכוּ֙ מִשֹּׁ֔ד מִצְרַ֥יִם תְּקַבְּצֵ֖ם מֹ֣ף תְּקַבְּרֵ֑ם מַחְמַ֣ד לְכַסְפָּ֗ם קִמּוֹשׂ֙ יִֽירָשֵׁ֔ם ח֖וֹחַ בְּאׇהֳלֵיהֶֽם׃",
      "es": "Pues he aquí que se fueron a causa de la destrucción; Mitsráyim los recogerá, Mof los sepultará; lo precioso de su plata, la ortiga lo heredará, espino habrá en sus tiendas.",
      "nota": "MOF — Nombre hebreo de la ciudad egipcia de Menfis, importante centro de la antigüedad."
    },
    {
      "num": 7,
      "he": "בָּ֣אוּ&thinsp;<b>׀</b> יְמֵ֣י הַפְּקֻדָּ֗ה בָּ֚אוּ יְמֵ֣י הַשִּׁלֻּ֔ם יֵדְע֖וּ יִשְׂרָאֵ֑ל אֱוִ֣יל הַנָּבִ֗יא מְשֻׁגָּע֙ אִ֣ישׁ הָר֔וּחַ עַ֚ל רֹ֣ב עֲוֺנְךָ֔ וְרַבָּ֖ה מַשְׂטֵמָֽה׃",
      "es": "Han llegado los días de la visitación, han llegado los días de la retribución; lo sabrá Yisrael. «¡Necio es el navi, enloquecido el hombre del espíritu!», por la grandeza de tu iniquidad y grande es la hostilidad.",
      "nota": "NAVI — Profeta; término hebreo que designa al portavoz de la palabra divina."
    },
    {
      "num": 8,
      "he": "צֹפֶ֥ה אֶפְרַ֖יִם עִם־אֱלֹהָ֑י נָבִ֞יא פַּ֤ח יָקוֹשׁ֙ עַל־כׇּל־דְּרָכָ֔יו מַשְׂטֵמָ֖ה בְּבֵ֥ית אֱלֹהָֽיו׃",
      "es": "Atalaya de Efráyim está con mi Elohim; el navi tiene trampa de cazador en todos sus caminos, hostilidad en la casa de su Elohim.",
      "nota": "NAVI — Profeta; mismo término que en el versículo anterior."
    },
    {
      "num": 9,
      "he": "הֶעְמִ֥יקוּ שִׁחֵ֖תוּ כִּימֵ֣י הַגִּבְעָ֑ה יִזְכּ֣וֹר עֲוֺנָ֔ם יִפְק֖וֹד חַטֹּאותָֽם׃&nbsp;<span class=\"mam-spi-samekh\">{ס}</span>&nbsp;&nbsp;&nbsp;&nbsp;&nbsp;&nbsp;&nbsp;&nbsp;",
      "es": "Se han corrompido profundamente como en los días de Guiveá; Él recordará su iniquidad, visitará sus pecados.",
      "nota": "GUIVEÁ — Ciudad benjaminita asociada al grave episodio de depravación narrado en Shofetim (Jueces) 19-20."
    },
    {
      "num": 10,
      "he": "כַּעֲנָבִ֣ים בַּמִּדְבָּ֗ר מָצָ֙אתִי֙ יִשְׂרָאֵ֔ל כְּבִכּוּרָ֤הֿ בִתְאֵנָה֙ בְּרֵ֣אשִׁיתָ֔הּ רָאִ֖יתִי אֲבוֹתֵיכֶ֑ם הֵ֜מָּה בָּ֣אוּ בַֽעַל־פְּע֗וֹר וַיִּנָּֽזְרוּ֙ לַבֹּ֔שֶׁת וַיִּהְי֥וּ שִׁקּוּצִ֖ים כְּאׇהֳבָֽם׃",
      "es": "Como uvas en el desierto hallé a Yisrael; como fruto temprano en la higuera, en su comienzo, vi a vuestros padres. Ellos vinieron a Baal Peor y se consagraron a la vergüenza, y se hicieron abominables como aquello que amaron.",
      "nota": "BAAL PEOR — Deidad cananea de la localidad de Peor; referencia al episodio de idolatría y licencia relatado en Bamidbar (Números) 25."
    },
    {
      "num": 11,
      "he": "אֶפְרַ֕יִם כָּע֖וֹף יִתְעוֹפֵ֣ף כְּבוֹדָ֑ם מִלֵּדָ֥ה וּמִבֶּ֖טֶן וּמֵהֵרָיֽוֹן׃",
      "es": "Efráyim: como ave volará su gloria; no habrá nacimiento, ni preñez, ni concepción."
    },
    {
      "num": 12,
      "he": "כִּ֤י אִם־יְגַדְּלוּ֙ אֶת־בְּנֵיהֶ֔ם וְשִׁכַּלְתִּ֖ים מֵאָדָ֑ם כִּֽי־גַם־א֥וֹי לָהֶ֖ם בְּשׂוּרִ֥י מֵהֶֽם׃",
      "es": "Aunque críen a sus hijos, los despojaré de ellos hasta no quedar hombre; pues también ¡ay de ellos cuando me aparte de ellos!"
    },
    {
      "num": 13,
      "he": "אֶפְרַ֛יִם כַּאֲשֶׁר־רָאִ֥יתִי לְצ֖וֹר שְׁתוּלָ֣ה בְנָוֶ֑ה וְאֶפְרַ֕יִם לְהוֹצִ֥יא אֶל־הֹרֵ֖ג בָּנָֽיו׃",
      "es": "Efráyim, según lo que vi, era como Tsor plantada en pradera; pero Efráyim habrá de sacar a sus hijos hacia el matador.",
      "nota": "TSOR — Ciudad fenicia costera, conocida por su esplendor y riqueza."
    },
    {
      "num": 14,
      "he": "תֵּן־לָהֶ֥ם יְהֹוָ֖ה מַה־תִּתֵּ֑ן תֵּן־לָהֶם֙ רֶ֣חֶם מַשְׁכִּ֔יל וְשָׁדַ֖יִם צֹמְקִֽים׃",
      "es": "Dales, oh Eterno, ¿qué les darás? Dales vientre que aborte y pechos secos.",
      "nota": "VIENTRE QUE ABORTE — Heb. רֶחֶם מַשְׁכִּיל (réjem mashkil), literalmente «vientre que hace perder»; designa un vientre que no lleva a término la gestación."
    },
    {
      "num": 15,
      "he": "כׇּל־רָעָתָ֤ם בַּגִּלְגָּל֙ כִּי־שָׁ֣ם שְׂנֵאתִ֔ים עַ֚ל רֹ֣עַ מַעַלְלֵיהֶ֔ם מִבֵּיתִ֖י אֲגָרְשֵׁ֑ם לֹ֤א אוֹסֵף֙ אַהֲבָתָ֔ם כׇּל־שָׂרֵיהֶ֖ם סֹרְרִֽים׃",
      "es": "Toda su maldad está en Guilgal, pues allí los aborrecí; por la maldad de sus obras, de mi Casa los expulsaré; no seguiré amándolos, todos sus príncipes son rebeldes.",
      "nota": "GUILGAL — Localidad en la tierra de Yisrael asociada a prácticas cultuales reprobadas por los profetas."
    },
    {
      "num": 16,
      "he": "הֻכָּ֣ה אֶפְרַ֔יִם שׇׁרְשָׁ֥ם יָבֵ֖שׁ פְּרִ֣י <span class=\"mam-kq\"><span class=\"mam-kq-k\">(בלי)</span> <span class=\"mam-kq-q\">[בַֽל־]</span></span>יַעֲשׂ֑וּן גַּ֚ם כִּ֣י יֵלֵד֔וּן וְהֵמַתִּ֖י מַחֲמַדֵּ֥י בִטְנָֽם׃",
      "es": "Herido ha sido Efráyim, su raíz se ha secado, fruto no producirán; aun cuando engendren, haré morir los preciados de su vientre."
    },
    {
      "num": 17,
      "he": "יִמְאָסֵ֣ם אֱלֹהַ֔י כִּ֛י לֹ֥א שָׁמְע֖וּ ל֑וֹ וְיִֽהְי֥וּ נֹדְדִ֖ים בַּגּוֹיִֽם׃&nbsp;<span class=\"mam-spi-samekh\">{ס}</span>&nbsp;&nbsp;&nbsp;&nbsp;&nbsp;&nbsp;&nbsp;&nbsp;",
      "es": "Los desechará mi Elohim, porque no le escucharon, y serán errantes entre las naciones.",
      "nota": "ELOHIM — Nombre divino; aquí con sufijo posesivo «mi Elohim»."
    }
  ]
}