{
  "book": "melakhim1",
  "book_he": "מְלָכִים א",
  "book_es": "1 Reyes",
  "chapter": 4,
  "title_he": "מלכים א",
  "verses": [
    {
      "num": 1,
      "he": "וַֽיְהִי֙ הַמֶּ֣לֶךְ שְׁלֹמֹ֔ה מֶ֖לֶךְ עַל־כׇּל־יִשְׂרָאֵֽל׃&nbsp;<span class=\"mam-spi-samekh\">{ס}</span>&nbsp;&nbsp;&nbsp;&nbsp;&nbsp;&nbsp;&nbsp;&nbsp;",
      "es": ""
    },
    {
      "num": 2,
      "he": "וְאֵ֥לֶּה הַשָּׂרִ֖ים אֲשֶׁר־ל֑וֹ עֲזַרְיָ֥הוּ בֶן־צָד֖וֹק הַכֹּהֵֽן׃&nbsp;<span class=\"mam-spi-samekh\">{ס}</span>&nbsp;&nbsp;&nbsp;&nbsp;&nbsp;&nbsp;&nbsp;&nbsp;",
      "es": ""
    },
    {
      "num": 3,
      "he": "אֱלִיחֹ֧רֶף וַאֲחִיָּ֛ה בְּנֵ֥י שִׁישָׁ֖א סֹפְרִ֑ים&nbsp;<span class=\"mam-spi-samekh\">{ס}</span>&nbsp;&nbsp;&nbsp;&nbsp;&nbsp;&nbsp;&nbsp;&nbsp;יְהוֹשָׁפָ֥ט בֶּן־אֲחִיל֖וּד הַמַּזְכִּֽיר׃&nbsp;<span class=\"mam-spi-samekh\">{ס}</span>&nbsp;&nbsp;&nbsp;&nbsp;&nbsp;&nbsp;&nbsp;&nbsp;",
      "es": ""
    },
    {
      "num": 4,
      "he": "וּבְנָיָ֥הוּ בֶן־יְהוֹיָדָ֖ע עַל־הַצָּבָ֑א&nbsp;<span class=\"mam-spi-samekh\">{ס}</span>&nbsp;&nbsp;&nbsp;&nbsp;&nbsp;&nbsp;&nbsp;&nbsp;וְצָד֥וֹק וְאֶבְיָתָ֖ר כֹּהֲנִֽים׃&nbsp;<span class=\"mam-spi-samekh\">{ס}</span>&nbsp;&nbsp;&nbsp;&nbsp;&nbsp;&nbsp;&nbsp;&nbsp;",
      "es": ""
    },
    {
      "num": 5,
      "he": "וַעֲזַרְיָ֥הוּ בֶן־נָתָ֖ן עַל־הַנִּצָּבִ֑ים&nbsp;<span class=\"mam-spi-samekh\">{ס}</span>&nbsp;&nbsp;&nbsp;&nbsp;&nbsp;&nbsp;&nbsp;&nbsp;וְזָב֧וּד בֶּן־נָתָ֛ן כֹּהֵ֖ן רֵעֶ֥ה הַמֶּֽלֶךְ׃&nbsp;<span class=\"mam-spi-samekh\">{ס}</span>&nbsp;&nbsp;&nbsp;&nbsp;&nbsp;&nbsp;&nbsp;&nbsp;",
      "es": ""
    },
    {
      "num": 6,
      "he": "וַאֲחִישָׁ֖ר עַל־הַבָּ֑יִת&nbsp;<span class=\"mam-spi-samekh\">{ס}</span>&nbsp;&nbsp;&nbsp;&nbsp;&nbsp;&nbsp;&nbsp;&nbsp;וַאֲדֹנִירָ֥ם בֶּן־עַבְדָּ֖א עַל־הַמַּֽס׃&nbsp;<span class=\"mam-spi-samekh\">{ס}</span>&nbsp;&nbsp;&nbsp;&nbsp;&nbsp;&nbsp;&nbsp;&nbsp;",
      "es": ""
    },
    {
      "num": 7,
      "he": "וְלִשְׁלֹמֹ֞ה שְׁנֵים־עָשָׂ֤ר נִצָּבִים֙ עַל־כׇּל־יִשְׂרָאֵ֔ל וְכִלְכְּל֥וּ אֶת־הַמֶּ֖לֶךְ וְאֶת־בֵּית֑וֹ חֹ֧דֶשׁ בַּשָּׁנָ֛ה יִהְיֶ֥ה עַל־<span class=\"mam-kq\"><span class=\"mam-kq-q\">[הָאֶחָ֖ד]</span> <span class=\"mam-kq-k\">(אחד)</span></span> לְכַלְכֵּֽל׃&nbsp;<span class=\"mam-spi-samekh\">{ס}</span>&nbsp;&nbsp;&nbsp;&nbsp;&nbsp;&nbsp;&nbsp;&nbsp;",
      "es": ""
    },
    {
      "num": 8,
      "he": "וְאֵ֣לֶּה שְׁמוֹתָ֔ם בֶּן־ח֖וּר בְּהַ֥ר אֶפְרָֽיִם׃&nbsp;<span class=\"mam-spi-samekh\">{ס}</span>&nbsp;&nbsp;&nbsp;&nbsp;&nbsp;&nbsp;&nbsp;&nbsp;",
      "es": ""
    },
    {
      "num": 9,
      "he": "בֶּן־דֶּ֛קֶר בְּמָקַ֥ץ וּבְשַׁעַלְבִ֖ים וּבֵ֣ית שָׁ֑מֶשׁ וְאֵיל֖וֹן בֵּ֥ית חָנָֽן׃&nbsp;<span class=\"mam-spi-samekh\">{ס}</span>&nbsp;&nbsp;&nbsp;&nbsp;&nbsp;&nbsp;&nbsp;&nbsp;",
      "es": ""
    },
    {
      "num": 10,
      "he": "בֶּן־חֶ֖סֶד בָּאֲרֻבּ֑וֹת ל֥וֹ שֹׂכֹ֖ה וְכׇל־אֶ֥רֶץ חֵֽפֶר׃&nbsp;<span class=\"mam-spi-samekh\">{ס}</span>&nbsp;&nbsp;&nbsp;&nbsp;&nbsp;&nbsp;&nbsp;&nbsp;",
      "es": ""
    },
    {
      "num": 11,
      "he": "בֶּן־אֲבִינָדָ֖ב כׇּל־נָ֣פַת דֹּ֑אר טָפַת֙ בַּת־שְׁלֹמֹ֔ה הָ֥יְתָה לּ֖וֹ לְאִשָּֽׁה׃&nbsp;<span class=\"mam-spi-samekh\">{ס}</span>&nbsp;&nbsp;&nbsp;&nbsp;&nbsp;&nbsp;&nbsp;&nbsp;",
      "es": ""
    },
    {
      "num": 12,
      "he": "בַּֽעֲנָא֙ בֶּן־אֲחִיל֔וּד תַּעְנַ֖ךְ וּמְגִדּ֑וֹ וְכׇל־בֵּ֣ית שְׁאָ֡ן אֲשֶׁר֩ אֵ֨צֶל צָרְתַ֜נָה מִתַּ֣חַת לְיִזְרְעֶ֗אל מִבֵּ֤ית שְׁאָן֙ עַ֚ד אָבֵ֣ל מְחוֹלָ֔ה עַ֖ד מֵעֵ֥בֶר לְיׇקְמְעָֽם׃&nbsp;<span class=\"mam-spi-samekh\">{ס}</span>&nbsp;&nbsp;&nbsp;&nbsp;&nbsp;&nbsp;&nbsp;&nbsp;",
      "es": ""
    },
    {
      "num": 13,
      "he": "בֶּן־גֶּ֖בֶר בְּרָמֹ֣ת גִּלְעָ֑ד ל֡וֹ חַוֺּת֩ יָאִ֨יר בֶּן־מְנַשֶּׁ֜ה אֲשֶׁ֣ר בַּגִּלְעָ֗ד ל֚וֹ חֶ֤בֶל אַרְגֹּב֙ אֲשֶׁ֣ר בַּבָּשָׁ֔ן שִׁשִּׁים֙ עָרִ֣ים גְּדֹל֔וֹת חוֹמָ֖ה וּבְרִ֥יחַ נְחֹֽשֶׁת׃&nbsp;<span class=\"mam-spi-samekh\">{ס}</span>&nbsp;&nbsp;&nbsp;&nbsp;&nbsp;&nbsp;&nbsp;&nbsp;",
      "es": ""
    },
    {
      "num": 14,
      "he": "אֲחִינָדָ֥ב בֶּן־עִדֹּ֖א מַחֲנָֽיְמָה׃&nbsp;<span class=\"mam-spi-samekh\">{ס}</span>&nbsp;&nbsp;&nbsp;&nbsp;&nbsp;&nbsp;&nbsp;&nbsp;",
      "es": ""
    },
    {
      "num": 15,
      "he": "אֲחִימַ֖עַץ בְּנַפְתָּלִ֑י גַּם־ה֗וּא לָקַ֛ח אֶת־בָּשְׂמַ֥ת בַּת־שְׁלֹמֹ֖ה לְאִשָּֽׁה׃&nbsp;<span class=\"mam-spi-samekh\">{ס}</span>&nbsp;&nbsp;&nbsp;&nbsp;&nbsp;&nbsp;&nbsp;&nbsp;",
      "es": ""
    },
    {
      "num": 16,
      "he": "בַּֽעֲנָא֙ בֶּן־חוּשָׁ֔י בְּאָשֵׁ֖ר וּבְעָלֽוֹת׃&nbsp;<span class=\"mam-spi-samekh\">{ס}</span>&nbsp;&nbsp;&nbsp;&nbsp;&nbsp;&nbsp;&nbsp;&nbsp;",
      "es": ""
    },
    {
      "num": 17,
      "he": "יְהוֹשָׁפָ֥ט בֶּן־פָּר֖וּחַ בְּיִשָּׂשכָֽר׃&nbsp;<span class=\"mam-spi-samekh\">{ס}</span>&nbsp;&nbsp;&nbsp;&nbsp;&nbsp;&nbsp;&nbsp;&nbsp;",
      "es": ""
    },
    {
      "num": 18,
      "he": "שִׁמְעִ֥י בֶן־אֵלָ֖א בְּבִנְיָמִֽן׃&nbsp;<span class=\"mam-spi-samekh\">{ס}</span>&nbsp;&nbsp;&nbsp;&nbsp;&nbsp;&nbsp;&nbsp;&nbsp;",
      "es": ""
    },
    {
      "num": 19,
      "he": "גֶּ֥בֶר בֶּן־אֻרִ֖י בְּאֶ֣רֶץ גִּלְעָ֑ד אֶ֜רֶץ סִיח֣וֹן&thinsp;<b>׀</b> מֶ֣לֶךְ הָאֱמֹרִ֗י וְעֹג֙ מֶ֣לֶךְ הַבָּשָׁ֔ן וּנְצִ֥יב אֶחָ֖ד אֲשֶׁ֥ר בָּאָֽרֶץ׃",
      "es": ""
    },
    {
      "num": 20,
      "he": "יְהוּדָ֤ה וְיִשְׂרָאֵל֙ רַבִּ֔ים כַּח֥וֹל אֲשֶׁר־עַל־הַיָּ֖ם לָרֹ֑ב אֹכְלִ֥ים וְשֹׁתִ֖ים וּשְׂמֵחִֽים׃",
      "es": ""
    }
  ]
}